emailproxy.py
emailproxy-2025.6.25.dist-info/licenses/LICENSE
emailproxy-2025.6.25.dist-info/METADATA
emailproxy-2025.6.25.dist-info/WHEEL
emailproxy-2025.6.25.dist-info/entry_points.txt
emailproxy-2025.6.25.dist-info/top_level.txt
emailproxy-2025.6.25.dist-info/RECORD
