Metadata-Version: 2.4
Name: emailproxy
Version: 2025.6.25
Summary: Transparently add OAuth 2.0 support to IMAP/POP/SMTP clients that don't support this authentication method.
Author-email: Simon Robinson <simon@robinson.ac>
License: Apache License 2.0
Project-URL: Documentation, https://github.com/simonrob/email-oauth2-proxy#email-oauth-20-proxy
Project-URL: Release Notes, https://github.com/simonrob/email-oauth2-proxy/releases
Project-URL: Report Issues, https://github.com/simonrob/email-oauth2-proxy/issues
Project-URL: Source Code, https://github.com/simonrob/email-oauth2-proxy
Classifier: Operating System :: OS Independent
Classifier: Operating System :: MacOS
Classifier: Operating System :: Microsoft :: Windows
Classifier: Operating System :: POSIX :: Linux
Classifier: Programming Language :: Python
Classifier: Topic :: Communications :: Email
Classifier: Topic :: Communications :: Email :: Mail Transport Agents
Classifier: Topic :: Communications :: Email :: Post-Office
Classifier: Topic :: Communications :: Email :: Post-Office :: IMAP
Classifier: Topic :: Communications :: Email :: Post-Office :: POP3
Classifier: Development Status :: 6 - Mature
Classifier: License :: OSI Approved :: Apache Software License
Requires-Python: >=3.7
License-File: LICENSE
Requires-Dist: cryptography>=2.2
Requires-Dist: pyasyncore; python_version >= "3.12"
Requires-Dist: pyoslog>=0.3.0; sys_platform == "darwin"
Requires-Dist: prompt_toolkit
Requires-Dist: pyjwt>=2.4
Provides-Extra: gui
Requires-Dist: importlib_metadata; python_version < "3.8" and extra == "gui"
Requires-Dist: packaging; extra == "gui"
Requires-Dist: pillow; extra == "gui"
Requires-Dist: timeago; extra == "gui"
Requires-Dist: pystray>=0.19.4; extra == "gui"
Requires-Dist: pywebview>=4.2.1; extra == "gui"
Requires-Dist: pyobjc-framework-Cocoa; sys_platform == "darwin" and extra == "gui"
Requires-Dist: pyobjc-framework-SystemConfiguration; sys_platform == "darwin" and extra == "gui"
Dynamic: license-file
